datatools/__init__.py
datatools/io_utils.py
datatools/load.py
datatools/merge_index.py
datatools/process.py
datatools/scripts/__init__.py
datatools/scripts/merge_index.py
datatools/scripts/pack.py
datatools/scripts/peek.py
datatools/scripts/tokenize.py
datatools/scripts/wrangle.py
datatools/scripts/tokenizers/__init__.py
datatools/scripts/tokenizers/llama2_tokenizer.py
datatools/scripts/tokenizers/llama3_tokenizer.py
datatools_py-0.5.dist-info/METADATA
datatools_py-0.5.dist-info/WHEEL
datatools_py-0.5.dist-info/entry_points.txt
datatools_py-0.5.dist-info/top_level.txt
datatools_py-0.5.dist-info/RECORD
