Metadata-Version: 2.4
Name: datatools-py
Version: 0.5
Summary: Library and scripts for common LM data utilities (tokenizing, splitting, packing, ...)
Home-page: https://github.com/CodeCreator/datatools
Author: Alexander Wettig
Classifier: Programming Language :: Python :: 3
Classifier: License :: OSI Approved :: MIT License
Classifier: Operating System :: OS Independent
Requires-Python: >=3.6
Requires-Dist: tqdm>=4.66.1
Requires-Dist: numpy>=1.26.4
Requires-Dist: simple_parsing>=0.1.5
Requires-Dist: mosaicml-streaming>=0.7.5
Requires-Dist: sentencepiece>=0.1.99
Requires-Dist: zstandard>=0.23.0
Requires-Dist: universal-pathlib>=0.2.2
Requires-Dist: fsspec[s3]>=2023.1.0
Requires-Dist: pyarrow>=10.0.0
Provides-Extra: datasets
Requires-Dist: datasets>=2.18.0; extra == "datasets"
Provides-Extra: full
Requires-Dist: datasets>=2.18.0; extra == "full"
Dynamic: author
Dynamic: classifier
Dynamic: description
Dynamic: description-content-type
Dynamic: home-page
Dynamic: provides-extra
Dynamic: requires-dist
Dynamic: requires-python
Dynamic: summary
